LICENSE
README.rst
anitya_schema/__init__.py
anitya_schema/base.py
anitya_schema/distro_messages.py
anitya_schema/project_messages.py
anitya_schema/tests/__init__.py
anitya_schema/tests/fixtures/org.release-monitoring.prod.anitya.distro.add.json
anitya_schema/tests/fixtures/org.release-monitoring.prod.anitya.distro.edit.json
anitya_schema/tests/fixtures/org.release-monitoring.prod.anitya.distro.remove.json
anitya_schema/tests/fixtures/org.release-monitoring.prod.anitya.project.add.json
anitya_schema/tests/fixtures/org.release-monitoring.prod.anitya.project.edit.json
anitya_schema/tests/fixtures/org.release-monitoring.prod.anitya.project.flag.json
anitya_schema/tests/fixtures/org.release-monitoring.prod.anitya.project.flag.set.json
anitya_schema/tests/fixtures/org.release-monitoring.prod.anitya.project.map.new.json
anitya_schema/tests/fixtures/org.release-monitoring.prod.anitya.project.map.remove.json
anitya_schema/tests/fixtures/org.release-monitoring.prod.anitya.project.map.update.json
anitya_schema/tests/fixtures/org.release-monitoring.prod.anitya.project.remove.json
anitya_schema/tests/fixtures/org.release-monitoring.prod.anitya.project.version.remove.json
anitya_schema/tests/fixtures/org.release-monitoring.prod.anitya.project.version.remove.v2.json
anitya_schema/tests/fixtures/org.release-monitoring.prod.anitya.project.version.update.json
anitya_schema/tests/fixtures/org.release-monitoring.prod.anitya.project.version.update.v2.json
anitya_schema/tests/test_base.py
anitya_schema/tests/test_distro_messages.py
anitya_schema/tests/test_project_messages.py
anitya_schema/tests/test_schema.py
anitya_schema-2.2.0.dist-info/entry_points.txt
anitya_schema-2.2.0.dist-info/LICENSE
anitya_schema-2.2.0.dist-info/WHEEL
anitya_schema-2.2.0.dist-info/METADATA
anitya_schema-2.2.0.dist-info/RECORD
