Metadata-Version: 2.1
Name: anitya-schema
Version: 2.2.0
Summary: JSON schema definitions for messages published by Anitya
Home-page: https://github.com/fedora-infra/anitya-messages
License: GPL-2.0-or-later
Author: Fedora Infrastructure Team
Author-email: infrastructure@lists.fedoraproject.org
Maintainer: Fedora Infrastructure Team
Maintainer-email: infrastructure@lists.fedoraproject.org
Requires-Python: >=3.8.1,<4.0.0
Classifier: License :: OSI Approved :: GNU General Public License v2 or later (GPLv2+)
Classifier: Programming Language :: Python :: 3
Classifier: Programming Language :: Python :: 3.10
Classifier: Programming Language :: Python :: 3.8
Classifier: Programming Language :: Python :: 3.9
Requires-Dist: fedora-messaging (>=3.1.0,<4.0.0)
Project-URL: Documentation, https://anitya-messages.readthedocs.io/en/latest
Project-URL: Repository, https://github.com/fedora-infra/anitya-messages
